ng_banks/__init__.py
ng_banks/example.py
ng_banks-1.0.1.dist-info/LICENSE
ng_banks-1.0.1.dist-info/METADATA
ng_banks-1.0.1.dist-info/WHEEL
ng_banks-1.0.1.dist-info/top_level.txt
ng_banks-1.0.1.dist-info/RECORD
