Metadata-Version: 2.1
Name: ng-banks
Version: 1.0.1
Summary: Python Implementation for Lightweight Zero dependency npm     package to get list of banks in Nigeria (Recognized by CBN)
Home-page: https://github.com/BolajiOlajide/ng_banks
Author: Bolaji Olajide
Author-email: cooproton@gmail.com
License: UNKNOWN
Keywords: banks,nigeria,nigerian,cbn
Platform: UNKNOWN
Classifier: Programming Language :: Python :: 3
Classifier: License :: OSI Approved :: MIT License
Classifier: Operating System :: OS Independent
